<?xml version = '1.0' encoding = 'UTF-8'?>
<Diagram class="oracle.dbtools.crest.swingui.relational.DPVRelational" name="Relational_1" id="ED42FE5D-5D77-1589-0FFD-3D6301F51111">
<createdBy>kauez</createdBy>
<modifiedBy>kauez</modifiedBy>
<createdTime>2023-11-19 20:22:10 UTC</createdTime>
<autoRoute>false</autoRoute>
<boxInbox>true</boxInbox>
<showLegend>false</showLegend>
<showLabels>false</showLabels>
<showRelAttributes>false</showRelAttributes>
<gridEnabled>false</gridEnabled>
<showGrid>false</showGrid>
<diagramColor>-1</diagramColor>
<display>false</display>
<notation>1</notation>
<objectViews>
<OView class="oracle.dbtools.crest.swingui.relational.TVTable" oid="0C5D7BD8-A883-619B-1041-C0B92D0CD1E0" otype="Table" vid="69D0B2A3-E6DE-5930-A48D-9AC66BE4D61A">
<hideElementsInCurrentOnly>false</hideElementsInCurrentOnly>
<bounds x="346" y="352" width="275" height="164"/>
</OView>
<OView class="oracle.dbtools.crest.swingui.relational.TVTable" oid="11088EA2-40FE-4454-E68E-0CAE09851394" otype="Table" vid="65241C4E-E041-BACC-CF4B-99238E74254D">
<hideElementsInCurrentOnly>false</hideElementsInCurrentOnly>
<bounds x="1129" y="430" width="272" height="149"/>
</OView>
<OView class="oracle.dbtools.crest.swingui.relational.TVTable" oid="13210832-19C7-A0EB-B3C7-62457B1F29C8" otype="Table" vid="7ECE8585-EE0E-2B82-924C-1AF5E5FDBEC2">
<hideElementsInCurrentOnly>false</hideElementsInCurrentOnly>
<bounds x="12" y="356" width="272" height="171"/>
</OView>
<OView class="oracle.dbtools.crest.swingui.relational.TVTable" oid="1C75C4A5-1769-B60B-63F9-0FF036DD09E9" otype="Table" vid="38187CCF-13CF-040A-D9FC-81D4DFBE7117">
<hideElementsInCurrentOnly>false</hideElementsInCurrentOnly>
<bounds x="677" y="0" width="324" height="255"/>
</OView>
<OView class="oracle.dbtools.crest.swingui.relational.TVTable" oid="2A85132B-B5AA-31A4-20BE-8BC460D4A221" otype="Table" vid="B3EC9754-8BCA-1958-E646-B538AA6628C5">
<hideElementsInCurrentOnly>false</hideElementsInCurrentOnly>
<bounds x="704" y="664" width="278" height="161"/>
</OView>
<OView class="oracle.dbtools.crest.swingui.relational.TVTable" oid="9A5C4A9D-4AD2-FD2D-23AF-FCD174EB7B84" otype="Table" vid="E50152D8-4271-54F9-83A6-ABECCCBCCA3B">
<hideElementsInCurrentOnly>false</hideElementsInCurrentOnly>
<bounds x="690" y="323" width="295" height="282"/>
</OView>
<OView class="oracle.dbtools.crest.swingui.relational.TVTable" oid="DAA23AAD-483B-D1AE-C29E-6AB3173E3543" otype="Table" vid="0F7582BB-32C5-14CB-D46C-C152DF57989A">
<hideElementsInCurrentOnly>false</hideElementsInCurrentOnly>
<bounds x="12" y="569" width="294" height="184"/>
</OView>
<OView class="oracle.dbtools.crest.swingui.relational.TVTable" oid="FE580744-90E0-E167-6634-AF61A59B5232" otype="Table" vid="D49E003F-9EF0-0184-5EF2-1E81944AFBDF">
<hideElementsInCurrentOnly>false</hideElementsInCurrentOnly>
<bounds x="1128" y="291" width="271" height="123"/>
</OView>
</objectViews>
<connectors>
<Connector class="oracle.dbtools.crest.swingui.relational.TVFKRelation" oid="1C554C07-EEAD-B3A8-E5A3-575D266683DE" otype="FKIndexAssociation" vid_source="69D0B2A3-E6DE-5930-A48D-9AC66BE4D61A" vid_target="7ECE8585-EE0E-2B82-924C-1AF5E5FDBEC2">
<hideElementsInCurrentOnly>false</hideElementsInCurrentOnly>
<backgroundColor>-16777216</backgroundColor>
<lineWidth>1</lineWidth>
<points>
<point x="346" y="451"/>
<point x="284" y="451"/>
</points>
</Connector>
<Connector class="oracle.dbtools.crest.swingui.relational.TVFKRelation" oid="4176DEB4-ED31-342C-065C-F59FABF1FAD6" otype="FKIndexAssociation" vid_source="69D0B2A3-E6DE-5930-A48D-9AC66BE4D61A" vid_target="E50152D8-4271-54F9-83A6-ABECCCBCCA3B">
<hideElementsInCurrentOnly>false</hideElementsInCurrentOnly>
<backgroundColor>-16777216</backgroundColor>
<lineWidth>1</lineWidth>
<points>
<point x="621" y="434"/>
<point x="690" y="434"/>
</points>
</Connector>
<Connector class="oracle.dbtools.crest.swingui.relational.TVFKRelation" oid="54BE02D0-E9CA-FD15-3238-3F0E9491CF2A" otype="FKIndexAssociation" vid_source="65241C4E-E041-BACC-CF4B-99238E74254D" vid_target="E50152D8-4271-54F9-83A6-ABECCCBCCA3B">
<hideElementsInCurrentOnly>false</hideElementsInCurrentOnly>
<backgroundColor>-16777216</backgroundColor>
<lineWidth>1</lineWidth>
<points>
<point x="1129" y="504"/>
<point x="985" y="504"/>
</points>
</Connector>
<Connector class="oracle.dbtools.crest.swingui.relational.TVFKRelation" oid="737B7FD9-0600-2086-E548-EF83491C3444" otype="FKIndexAssociation" vid_source="7ECE8585-EE0E-2B82-924C-1AF5E5FDBEC2" vid_target="0F7582BB-32C5-14CB-D46C-C152DF57989A">
<hideElementsInCurrentOnly>false</hideElementsInCurrentOnly>
<backgroundColor>-16777216</backgroundColor>
<lineWidth>1</lineWidth>
<points>
<point x="148" y="527"/>
<point x="148" y="569"/>
</points>
</Connector>
<Connector class="oracle.dbtools.crest.swingui.relational.TVFKRelation" oid="97F6C508-DB29-B031-EBDD-DE7869E8B6AF" otype="FKIndexAssociation" vid_source="D49E003F-9EF0-0184-5EF2-1E81944AFBDF" vid_target="E50152D8-4271-54F9-83A6-ABECCCBCCA3B">
<hideElementsInCurrentOnly>false</hideElementsInCurrentOnly>
<backgroundColor>-16777216</backgroundColor>
<lineWidth>1</lineWidth>
<points>
<point x="1128" y="368"/>
<point x="985" y="368"/>
</points>
</Connector>
<Connector class="oracle.dbtools.crest.swingui.relational.TVFKRelation" oid="9E293DC8-3C4A-5F45-9E6E-3F26382949A8" otype="FKIndexAssociation" vid_source="38187CCF-13CF-040A-D9FC-81D4DFBE7117" vid_target="E50152D8-4271-54F9-83A6-ABECCCBCCA3B">
<hideElementsInCurrentOnly>false</hideElementsInCurrentOnly>
<backgroundColor>-16777216</backgroundColor>
<lineWidth>1</lineWidth>
<points>
<point x="837" y="255"/>
<point x="837" y="323"/>
</points>
</Connector>
<Connector class="oracle.dbtools.crest.swingui.relational.TVFKRelation" oid="CA8A55E4-8EA6-25F1-9893-AA9F9774A9EF" otype="FKIndexAssociation" vid_source="B3EC9754-8BCA-1958-E646-B538AA6628C5" vid_target="E50152D8-4271-54F9-83A6-ABECCCBCCA3B">
<hideElementsInCurrentOnly>false</hideElementsInCurrentOnly>
<backgroundColor>-16777216</backgroundColor>
<lineWidth>1</lineWidth>
<points>
<point x="843" y="664"/>
<point x="843" y="605"/>
</points>
</Connector>
</connectors>
</Diagram>
